pydynotree/pydynotree.pyi
pydynotree/__init__.py
pydynotree/quim_add.py
pydynotree/pydynotree.cpython-311-x86_64-linux-gnu.so
pydynotree-0.0.8.dist-info/WHEEL
pydynotree-0.0.8.dist-info/RECORD
pydynotree-0.0.8.dist-info/METADATA
pydynotree-0.0.8.dist-info/top_level.txt
pydynotree-0.0.8.dist-info/LICENSE.txt
